revjwt/__init__.py
revjwt/algorithms.py
revjwt/cert.py
revjwt/decode_static.py
revjwt/google_jwt.py
revjwt/jws.py
revjwt/jwt.py
revjwt/kms_encode.py
revjwt/py.typed
revjwt/signer.py
revjwt/utils.py
revjwt-1.0.7.dist-info/WHEEL
revjwt-1.0.7.dist-info/METADATA
revjwt-1.0.7.dist-info/RECORD
